counter/counter_sim/counter.v
module counter(clk,rst,q);

input clk,rst;
output reg [3:0]q;

always@(posedge clk)
if(rst)
q<=0;
else
q<=q+1;

endmodule

counter/test_counter.v
`timescale 1ns/1ns
module test_counter;

reg clk,rst;
wire [3:0]q;

counter dut(clk,rst,q);

initial begin
$dumpvars(1);
$dumpfile("wave.vcd");
end

initial begin
clk=0;
rst=0;
#5 rst=1;
#4 rst=0;
end

always #5 clk=~clk;

initial
begin
$monitor($time,"clk=%b rst=%b q=%0d",clk,rst,q);
#300;
$stop;
end
endmodule

counter/counter_sim/dump.vcd
$date
	Wed Oct  4 17:47:27 2023
$end
$version
	Icarus Verilog
$end
$timescale
	1ns
$end
$scope module test_counter $end
$var wire 4 ! q [3:0] $end
$var reg 1 " clk $end
$var reg 1 # rst $end
$upscope $end
$enddefinitions $end
$comment Show the parameter values. $end
$dumpall
$end
#0
$dumpvars
0#
0"
bx !
$end
#5
b0 !
1"
1#
#9
0#
#10
0"
#15
b1 !
1"
#20
0"
#25
b10 !
1"
#30
0"
#35
b11 !
1"
#40
0"
#45
b100 !
1"
#50
0"
#55
b101 !
1"
#60
0"
#65
b110 !
1"
#70
0"
#75
b111 !
1"
#80
0"
#85
b1000 !
1"
#90
0"
#95
b1001 !
1"
#100
0"
#105
b1010 !
1"
#110
0"
#115
b1011 !
1"
#120
0"
#125
b1100 !
1"
#130
0"
#135
b1101 !
1"
#140
0"
#145
b1110 !
1"
#150
0"
#155
b1111 !
1"
#160
0"
#165
b0 !
1"
#170
0"
#175
b1 !
1"
#180
0"
#185
b10 !
1"
#190
0"
#195
b11 !
1"
#200
0"
#205
b100 !
1"
#210
0"
#215
b101 !
1"
#220
0"
#225
b110 !
1"
#230
0"
#235
b111 !
1"
#240
0"
#245
b1000 !
1"
#250
0"
#255
b1001 !
1"
#260
0"
#265
b1010 !
1"
#270
0"
#275
b1011 !
1"
#280
0"
#285
b1100 !
1"
#290
0"
#295
b1101 !
1"
